bayspline/__init__.py
bayspline/plot.py
bayspline/predict.py
bayspline/utils.py
bayspline/example_data/tierney2016-p178-15p.csv
bayspline/modelparams/__init__.py
bayspline/modelparams/bayes_posterior.mat
bayspline/modelparams/core.py
bayspline/tests/__init__.py
bayspline/tests/test_predict_sst.py
bayspline/tests/test_predict_uk.py
bayspline/tests/test_utils.py
baysplinepy-0.0.2.dist-info/LICENSE
baysplinepy-0.0.2.dist-info/METADATA
baysplinepy-0.0.2.dist-info/WHEEL
baysplinepy-0.0.2.dist-info/top_level.txt
baysplinepy-0.0.2.dist-info/RECORD
