Metadata-Version: 2.1
Name: baysplinepy
Version: 0.0.2
Summary: A Python implementation of BAYSPLINE
Home-page: https://github.com/brews/baysplinepy
Author: S. Brewster Malevich
Author-email: malevich@email.arizona.edu
License: GPLv3
Keywords: marine paleoclimate uk37 calibration
Platform: UNKNOWN
Classifier: Development Status :: 3 - Alpha
Classifier: Intended Audience :: Developers
Classifier: Intended Audience :: Science/Research
Classifier: Topic :: Scientific/Engineering
Classifier: License :: OSI Approved :: GNU General Public License v3 or later (GPLv3+)
Classifier: Programming Language :: Python :: 3
Requires-Dist: numpy
Requires-Dist: scipy
Requires-Dist: matplotlib
Requires-Dist: tqdm
Requires-Dist: attrs
